console/__init__.py
console/exe.py
secuer/__init__.py
secuer/secuer.py
secuer/secuerconsensus.py
shijie-3.0.dist-info/LICENSE.txt
shijie-3.0.dist-info/METADATA
shijie-3.0.dist-info/WHEEL
shijie-3.0.dist-info/entry_points.txt
shijie-3.0.dist-info/top_level.txt
shijie-3.0.dist-info/RECORD
